delpy
