Metadata-Version: 1.1
Name: delpy
Version: 2017.12.12a0.dev2
Summary: Blockly w/ Python on Jupyter Notebook
Home-page: https://github.com/gwangyi/delpy
Author: Sungkwang Lee
Author-email: gwangyi.kr@gmail.com
License: MIT
Platform: UNKNOWN
Classifier: Development Status :: 3 - Alpha
Classifier: Programming Language :: Python :: 3
Classifier: Programming Language :: Python :: 3.6
